pyaaware/__init__.py
pyaaware/compress.py
pyaaware/constants.py
pyaaware/env_vars.py
pyaaware/feature_generator.py
pyaaware/feature_generator_parser.py
pyaaware/nnp_detect.py
pyaaware/py.typed
pyaaware/rs.abi3.so
pyaaware/rs.pyi
pyaaware/rust/__init__.py
pyaaware/sed.py
pyaaware/stacked_complex.py
pyaaware/torch/__init__.py
pyaaware/torch/compress.py
pyaaware/torch/forward_transform.py
pyaaware/torch/inverse_transform.py
pyaaware/torch/transform_types.py
pyaaware/write_wav.py
pyaaware-2.5.1.dist-info/METADATA
pyaaware-2.5.1.dist-info/WHEEL
pyaaware.libs/libgomp-a49a47f9.so.1
pyaaware.libs/libsoxr-25bd9ddc.so.0
pyaaware-2.5.1.dist-info/RECORD
