Metadata-Version: 2.4
Name: pyaaware
Version: 2.5.1
Requires-Dist: librosa>=0.10.2.post1,<1.0
Requires-Dist: pydub>=0.25.1,<1.0
Requires-Dist: numpy>=2,<2.3
Requires-Dist: soundfile>=0.12.1,<1.0
Requires-Dist: torch>=2.8,<3.0
Summary: Aaware development libraries
Author-email: Jason Calderwood <jason@aaware.com>
License-Expression: GPL-3.0-only
Requires-Python: >=3.11, <3.12
Project-URL: Homepage, https://aaware.com
